[
  {
    "category": "Smart Wearables",
    "sub": "Smart Watches",
    "title": "TechWatch X",
    "price": "$199",
    "image": "https://images.unsplash.com/photo-1511707171634-5f897ff02aa9?fit=crop&w=400&h=500"
  },
  {
    "category": "LED Fashion",
    "sub": "LED T-Shirts",
    "title": "Glow Tee",
    "price": "$59",
    "image": "https://images.unsplash.com/photo-1532339142462-99e8c7d8519f?fit=crop&w=400&h=500"
  },
  {
    "category": "3D Printed",
    "sub": "3D Printed Shoes",
    "title": "PrintStep",
    "price": "$149",
    "image": "https://images.unsplash.com/photo-1600181959312-c7f28b1f3be1?fit=crop&w=400&h=500"
  },
  {
    "category": "Eco-Tech Clothing",
    "sub": "Recycled Smart Materials",
    "title": "Eco Jacket",
    "price": "$99",
    "image": "https://images.unsplash.com/photo-1602810319226-3b25f3e6231b?fit=crop&w=400&h=500"
  },
  {
    "category": "Heated Jackets",
    "sub": "Bluetooth Controlled",
    "title": "WarmZone Pro",
    "price": "$189",
    "image": "https://images.unsplash.com/photo-1600181959312-c7f28b1f3be1?fit=crop&w=400&h=500"
  }
]